CORAL/__init__.py
CORAL/_version.py
CORAL/library.py
CORAL/manager.py
CORAL/pipelines.py
CORAL/utils.py
coral_nrel-0.1.2.dist-info/METADATA
coral_nrel-0.1.2.dist-info/WHEEL
coral_nrel-0.1.2.dist-info/top_level.txt
coral_nrel-0.1.2.dist-info/RECORD
