Metadata-Version: 2.1
Name: coral-nrel
Version: 0.1.2
Summary: Concurrent ORBIT for shared Resource Analysis Library
Author: Jake Nunemaker
Requires-Dist: numpy
Requires-Dist: pandas
Requires-Dist: marmot-agents (>=0.2.5)
Requires-Dist: orbit-nrel (>=1.0.6)
Requires-Dist: matplotlib
Requires-Dist: jupyterlab
Provides-Extra: dev
Requires-Dist: pre-commit ; extra == 'dev'
Requires-Dist: pylint ; extra == 'dev'
Requires-Dist: flake8 ; extra == 'dev'
Requires-Dist: black ; extra == 'dev'
Requires-Dist: isort ; extra == 'dev'
Requires-Dist: pytest ; extra == 'dev'
Requires-Dist: sphinx ; extra == 'dev'
Requires-Dist: sphinx-rtd-theme ; extra == 'dev'
